MANIFEST.in
README.txt
setup.py
XStatic_BootstrapTagsInput.egg-info/PKG-INFO
XStatic_BootstrapTagsInput.egg-info/SOURCES.txt
XStatic_BootstrapTagsInput.egg-info/dependency_links.txt
XStatic_BootstrapTagsInput.egg-info/namespace_packages.txt
XStatic_BootstrapTagsInput.egg-info/not-zip-safe
XStatic_BootstrapTagsInput.egg-info/top_level.txt
xstatic/__init__.py
xstatic/pkg/__init__.py
xstatic/pkg/bootstraptagsinput/.DS_Store
xstatic/pkg/bootstraptagsinput/__init__.py
xstatic/pkg/bootstraptagsinput/data/.DS_Store
xstatic/pkg/bootstraptagsinput/data/bootstrap-tagsinput.css
xstatic/pkg/bootstraptagsinput/data/bootstrap-tagsinput.js
xstatic/pkg/bootstraptagsinput/data/bootstrap-tagsinput.min.js
xstatic/pkg/bootstraptagsinput/data/bootstrap-tagsinput.min.js.map