Metadata-Version: 1.0
Name: XStatic-BootstrapTagsInput
Version: 0.5.1
Summary: BootstrapTagsInput 0.5 (XStatic packaging standard)
Home-page: http://timschlechter.github.io/bootstrap-tagsinput/examples/
Author: Yask Srivastava
Author-email: yask123@gmail.com
License: (same as BootstrapTagsInput)
Keywords: bootstraptagsinput xstatic
Platform: any
